bricklink_py/__init__.py
bricklink_py/bricklink.py
bricklink_py/catalog_item.py
bricklink_py/category.py
bricklink_py/color.py
bricklink_py/coupon.py
bricklink_py/feedback.py
bricklink_py/item_mapping.py
bricklink_py/member.py
bricklink_py/order.py
bricklink_py/push_notification.py
bricklink_py/setting.py
bricklink_py/store_inventory.py
bricklink_py/utils.py
bricklink_py-0.1.0.dist-info/LICENSE
bricklink_py-0.1.0.dist-info/METADATA
bricklink_py-0.1.0.dist-info/WHEEL
bricklink_py-0.1.0.dist-info/top_level.txt
bricklink_py-0.1.0.dist-info/RECORD
