Metadata-Version: 2.1
Name: bricklink_py
Version: 0.1.0
Summary: Python client for the BrickLink API
Author-email: Juan Franco <bricklink_py@juanfg.es>
License: AGPL-3.0-or-later
Project-URL: Homepage, https://github.com/FrogCosmonaut/bricklink_py
Project-URL: Bug Tracker, https://github.com/FrogCosmonaut/bricklink_py/issues
Classifier: Programming Language :: Python :: 3
Classifier: License :: OSI Approved :: GNU Affero General Public License v3 or later (AGPLv3+)
Classifier: Operating System :: OS Independent
Requires-Python: >=3.8
License-File: LICENSE
Requires-Dist: requests-oauthlib
